{"v":5,"entries":{"reshaped-design-system-badge--default":{"type":"story","id":"reshaped-design-system-badge--default","name":"Default","title":"Reshaped Design System/Badge","importPath":"./stories/Badge.stories.js","componentPath":"./stories/Badge.jsx","tags":["dev","test"]},"reshaped-design-system-badge--primary":{"type":"story","id":"reshaped-design-system-badge--primary","name":"Primary","title":"Reshaped Design System/Badge","importPath":"./stories/Badge.stories.js","componentPath":"./stories/Badge.jsx","tags":["dev","test"]},"reshaped-design-system-badge--success":{"type":"story","id":"reshaped-design-system-badge--success","name":"Success","title":"Reshaped Design System/Badge","importPath":"./stories/Badge.stories.js","componentPath":"./stories/Badge.jsx","tags":["dev","test"]},"reshaped-design-system-badge--warning":{"type":"story","id":"reshaped-design-system-badge--warning","name":"Warning","title":"Reshaped Design System/Badge","importPath":"./stories/Badge.stories.js","componentPath":"./stories/Badge.jsx","tags":["dev","test"]},"reshaped-design-system-badge--error":{"type":"story","id":"reshaped-design-system-badge--error","name":"Error","title":"Reshaped Design System/Badge","importPath":"./stories/Badge.stories.js","componentPath":"./stories/Badge.jsx","tags":["dev","test"]},"reshaped-design-system-badge--info":{"type":"story","id":"reshaped-design-system-badge--info","name":"Info","title":"Reshaped Design System/Badge","importPath":"./stories/Badge.stories.js","componentPath":"./stories/Badge.jsx","tags":["dev","test"]},"reshaped-design-system-badge--outline":{"type":"story","id":"reshaped-design-system-badge--outline","name":"Outline","title":"Reshaped Design System/Badge","importPath":"./stories/Badge.stories.js","componentPath":"./stories/Badge.jsx","tags":["dev","test"]},"reshaped-design-system-badge--small":{"type":"story","id":"reshaped-design-system-badge--small","name":"Small","title":"Reshaped Design System/Badge","importPath":"./stories/Badge.stories.js","componentPath":"./stories/Badge.jsx","tags":["dev","test"]},"reshaped-design-system-badge--large":{"type":"story","id":"reshaped-design-system-badge--large","name":"Large","title":"Reshaped Design System/Badge","importPath":"./stories/Badge.stories.js","componentPath":"./stories/Badge.jsx","tags":["dev","test"]},"reshaped-design-system-badge--all-variants":{"type":"story","id":"reshaped-design-system-badge--all-variants","name":"All Variants","title":"Reshaped Design System/Badge","importPath":"./stories/Badge.stories.js","componentPath":"./stories/Badge.jsx","tags":["dev","test"]},"reshaped-design-system-button--primary":{"type":"story","id":"reshaped-design-system-button--primary","name":"Primary","title":"Reshaped Design System/Button","importPath":"./stories/Button.stories.js","componentPath":"./stories/Button.jsx","tags":["dev","test"]},"reshaped-design-system-button--secondary":{"type":"story","id":"reshaped-design-system-button--secondary","name":"Secondary","title":"Reshaped Design System/Button","importPath":"./stories/Button.stories.js","componentPath":"./stories/Button.jsx","tags":["dev","test"]},"reshaped-design-system-button--outline":{"type":"story","id":"reshaped-design-system-button--outline","name":"Outline","title":"Reshaped Design System/Button","importPath":"./stories/Button.stories.js","componentPath":"./stories/Button.jsx","tags":["dev","test"]},"reshaped-design-system-button--ghost":{"type":"story","id":"reshaped-design-system-button--ghost","name":"Ghost","title":"Reshaped Design System/Button","importPath":"./stories/Button.stories.js","componentPath":"./stories/Button.jsx","tags":["dev","test"]},"reshaped-design-system-button--small":{"type":"story","id":"reshaped-design-system-button--small","name":"Small","title":"Reshaped Design System/Button","importPath":"./stories/Button.stories.js","componentPath":"./stories/Button.jsx","tags":["dev","test"]},"reshaped-design-system-button--large":{"type":"story","id":"reshaped-design-system-button--large","name":"Large","title":"Reshaped Design System/Button","importPath":"./stories/Button.stories.js","componentPath":"./stories/Button.jsx","tags":["dev","test"]},"reshaped-design-system-button--disabled":{"type":"story","id":"reshaped-design-system-button--disabled","name":"Disabled","title":"Reshaped Design System/Button","importPath":"./stories/Button.stories.js","componentPath":"./stories/Button.jsx","tags":["dev","test"]},"reshaped-design-system-card--default":{"type":"story","id":"reshaped-design-system-card--default","name":"Default","title":"Reshaped Design System/Card","importPath":"./stories/Card.stories.js","componentPath":"./stories/Card.jsx","tags":["dev","test"]},"reshaped-design-system-card--elevated":{"type":"story","id":"reshaped-design-system-card--elevated","name":"Elevated","title":"Reshaped Design System/Card","importPath":"./stories/Card.stories.js","componentPath":"./stories/Card.jsx","tags":["dev","test"]},"reshaped-design-system-card--outlined":{"type":"story","id":"reshaped-design-system-card--outlined","name":"Outlined","title":"Reshaped Design System/Card","importPath":"./stories/Card.stories.js","componentPath":"./stories/Card.jsx","tags":["dev","test"]},"reshaped-design-system-card--filled":{"type":"story","id":"reshaped-design-system-card--filled","name":"Filled","title":"Reshaped Design System/Card","importPath":"./stories/Card.stories.js","componentPath":"./stories/Card.jsx","tags":["dev","test"]},"reshaped-design-system-card--hoverable":{"type":"story","id":"reshaped-design-system-card--hoverable","name":"Hoverable","title":"Reshaped Design System/Card","importPath":"./stories/Card.stories.js","componentPath":"./stories/Card.jsx","tags":["dev","test"]},"reshaped-design-system-card--clickable":{"type":"story","id":"reshaped-design-system-card--clickable","name":"Clickable","title":"Reshaped Design System/Card","importPath":"./stories/Card.stories.js","componentPath":"./stories/Card.jsx","tags":["dev","test"]},"reshaped-design-system-card--large-padding":{"type":"story","id":"reshaped-design-system-card--large-padding","name":"Large Padding","title":"Reshaped Design System/Card","importPath":"./stories/Card.stories.js","componentPath":"./stories/Card.jsx","tags":["dev","test"]},"reshaped-design-system-card--no-padding":{"type":"story","id":"reshaped-design-system-card--no-padding","name":"No Padding","title":"Reshaped Design System/Card","importPath":"./stories/Card.stories.js","componentPath":"./stories/Card.jsx","tags":["dev","test"]},"reshaped-design-system-input--default":{"type":"story","id":"reshaped-design-system-input--default","name":"Default","title":"Reshaped Design System/Input","importPath":"./stories/Input.stories.js","componentPath":"./stories/Input.jsx","tags":["dev","test"]},"reshaped-design-system-input--with-helper-text":{"type":"story","id":"reshaped-design-system-input--with-helper-text","name":"With Helper Text","title":"Reshaped Design System/Input","importPath":"./stories/Input.stories.js","componentPath":"./stories/Input.jsx","tags":["dev","test"]},"reshaped-design-system-input--error":{"type":"story","id":"reshaped-design-system-input--error","name":"Error","title":"Reshaped Design System/Input","importPath":"./stories/Input.stories.js","componentPath":"./stories/Input.jsx","tags":["dev","test"]},"reshaped-design-system-input--disabled":{"type":"story","id":"reshaped-design-system-input--disabled","name":"Disabled","title":"Reshaped Design System/Input","importPath":"./stories/Input.stories.js","componentPath":"./stories/Input.jsx","tags":["dev","test"]},"reshaped-design-system-input--small":{"type":"story","id":"reshaped-design-system-input--small","name":"Small","title":"Reshaped Design System/Input","importPath":"./stories/Input.stories.js","componentPath":"./stories/Input.jsx","tags":["dev","test"]},"reshaped-design-system-input--large":{"type":"story","id":"reshaped-design-system-input--large","name":"Large","title":"Reshaped Design System/Input","importPath":"./stories/Input.stories.js","componentPath":"./stories/Input.jsx","tags":["dev","test"]},"reshaped-design-system-input--password":{"type":"story","id":"reshaped-design-system-input--password","name":"Password","title":"Reshaped Design System/Input","importPath":"./stories/Input.stories.js","componentPath":"./stories/Input.jsx","tags":["dev","test"]},"reshaped-design-system-modal--default":{"type":"story","id":"reshaped-design-system-modal--default","name":"Default","title":"Reshaped Design System/Modal","importPath":"./stories/Modal.stories.js","componentPath":"./stories/Modal.jsx","tags":["dev","test"]},"reshaped-design-system-modal--small":{"type":"story","id":"reshaped-design-system-modal--small","name":"Small","title":"Reshaped Design System/Modal","importPath":"./stories/Modal.stories.js","componentPath":"./stories/Modal.jsx","tags":["dev","test"]},"reshaped-design-system-modal--large":{"type":"story","id":"reshaped-design-system-modal--large","name":"Large","title":"Reshaped Design System/Modal","importPath":"./stories/Modal.stories.js","componentPath":"./stories/Modal.jsx","tags":["dev","test"]},"reshaped-design-system-modal--without-close-button":{"type":"story","id":"reshaped-design-system-modal--without-close-button","name":"Without Close Button","title":"Reshaped Design System/Modal","importPath":"./stories/Modal.stories.js","componentPath":"./stories/Modal.jsx","tags":["dev","test"]},"reshaped-design-system-modal--without-title":{"type":"story","id":"reshaped-design-system-modal--without-title","name":"Without Title","title":"Reshaped Design System/Modal","importPath":"./stories/Modal.stories.js","componentPath":"./stories/Modal.jsx","tags":["dev","test"]},"reshaped-design-system-modal--fullscreen":{"type":"story","id":"reshaped-design-system-modal--fullscreen","name":"Fullscreen","title":"Reshaped Design System/Modal","importPath":"./stories/Modal.stories.js","componentPath":"./stories/Modal.jsx","tags":["dev","test"]}}}